checkpoint_engine/__init__.py
checkpoint_engine/__main__.py
checkpoint_engine/_version.py
checkpoint_engine/api.py
checkpoint_engine/data_types.py
checkpoint_engine/device_utils.py
checkpoint_engine/p2p_store.py
checkpoint_engine/pin_memory.py
checkpoint_engine/ps.py
checkpoint_engine/worker.py
checkpoint_engine-0.3.2.dist-info/licenses/LICENCE
checkpoint_engine-0.3.2.dist-info/METADATA
checkpoint_engine-0.3.2.dist-info/WHEEL
checkpoint_engine-0.3.2.dist-info/top_level.txt
checkpoint_engine-0.3.2.dist-info/RECORD
