Metadata-Version: 2.4
Name: checkpoint-engine
Version: 0.3.2
Summary: checkpoint-engine is a lightweight, decoupling and efficient weight update middleware
Project-URL: Homepage, https://github.com/MoonshotAI/checkpoint-engine
Project-URL: Repository, https://github.com/MoonshotAI/checkpoint-engine
Project-URL: Documentation, https://github.com/MoonshotAI/checkpoint-engine
Project-URL: Issue Tracker, https://github.com/MoonshotAI/checkpoint-engine/issues
Requires-Python: >=3.10
License-File: LICENCE
Requires-Dist: torch>=2.5.0
Requires-Dist: fastapi
Requires-Dist: pydantic>=2.0.0
Requires-Dist: safetensors
Requires-Dist: pyzmq
Requires-Dist: uvicorn
Requires-Dist: loguru
Requires-Dist: numpy
Requires-Dist: httpx
Provides-Extra: p2p
Requires-Dist: mooncake-transfer-engine>=0.3.5; extra == "p2p"
Dynamic: license-file
